wagtail_draftail_plugins/__init__.py
wagtail_draftail_plugins/locale/es/LC_MESSAGES/django.mo
wagtail_draftail_plugins/locale/es/LC_MESSAGES/django.po
wagtail_draftail_plugins/py.typed
wagtail_draftail_plugins/wagtail_hooks.py
wagtail_draftail_plugins-0.4.0.dist-info/LICENSE
wagtail_draftail_plugins-0.4.0.dist-info/METADATA
wagtail_draftail_plugins-0.4.0.dist-info/WHEEL
wagtail_draftail_plugins-0.4.0.dist-info/RECORD
